Metadata-Version: 2.1
Name: play-selenium
Version: 0.0.2
Summary: pytest plugin that let you drive a browser with Selenium
Home-page: https://github.com/davidemoro/play_selenium
Author: Davide Moro
Author-email: davide.moro@gmail.com
Maintainer: Davide Moro
Maintainer-email: davide.moro@gmail.com
License: Apache Software License 2.0
Platform: UNKNOWN
Classifier: Development Status :: 2 - Pre-Alpha
Classifier: Framework :: Pytest
Classifier: Intended Audience :: Developers
Classifier: Topic :: Software Development :: Testing
Classifier: Programming Language :: Python
Classifier: Programming Language :: Python :: 2
Classifier: Programming Language :: Python :: 2.7
Classifier: Programming Language :: Python :: 3
Classifier: Programming Language :: Python :: 3.6
Classifier: Programming Language :: Python :: Implementation :: CPython
Classifier: Programming Language :: Python :: Implementation :: PyPy
Classifier: Operating System :: OS Independent
Classifier: License :: OSI Approved :: Apache Software License
Provides-Extra: docs
Provides-Extra: tests
